{
    "fluentMethods": true,
    "relationships": [
        {
            "relationshipName": "sale",
            "otherEntityName": "sale",
            "relationshipType": "many-to-many",
            "ownerSide": false,
            "otherEntityRelationshipName": "product"
        }
    ],
    "fields": [
        {
            "fieldName": "name",
            "fieldType": "String",
            "fieldValidateRules": [
                "required"
            ]
        }
    ],
    "changelogDate": "20170131113936",
    "dto": "no",
    "service": "serviceImpl",
    "entityTableName": "product",
    "pagination": "infinite-scroll"
}
